task.py
g16/__init__.py
g16/g16_client.py
g16/g16_server.py
g16/g16_struct.py
qcrun-2025.6.11.post1.dist-info/METADATA
qcrun-2025.6.11.post1.dist-info/WHEEL
qcrun-2025.6.11.post1.dist-info/entry_points.txt
qcrun-2025.6.11.post1.dist-info/top_level.txt
qcrun-2025.6.11.post1.dist-info/RECORD
