Metadata-Version: 2.4
Name: qcrun
Version: 2025.6.11.post1
Summary: dft runner
Author-email: ShangChien <hi@emm.sh>
Maintainer-email: ShangChien <hi@emm.sh>
License-Expression: GPL-3.0
Project-URL: Homepage, https://example.com
Project-URL: Documentation, https://readthedocs.org
Keywords: dft,gaussian,orca,vasp,pyscf,cp2k
Classifier: Programming Language :: Python
Requires-Python: >=3.10
Requires-Dist: numpy
Requires-Dist: pydantic
Requires-Dist: ase
Requires-Dist: fchic
